{
  "factor": "StarSearch",
  "asof": "2026-05-25",
  "months": [
    "2005-01",
    "2005-02",
    "2005-03",
    "2005-04",
    "2005-05",
    "2005-06",
    "2005-07",
    "2005-09",
    "2005-10",
    "2005-11",
    "2005-12",
    "2006-01",
    "2006-02",
    "2006-03",
    "2006-04",
    "2006-05",
    "2006-06",
    "2006-07",
    "2006-08",
    "2006-09",
    "2006-10",
    "2006-11",
    "2006-12",
    "2007-01",
    "2007-02",
    "2007-03",
    "2007-04",
    "2007-05",
    "2007-06",
    "2007-07",
    "2007-08",
    "2007-09",
    "2007-10",
    "2007-11",
    "2007-12",
    "2008-01",
    "2008-02",
    "2008-03",
    "2008-04",
    "2008-05",
    "2008-06",
    "2008-07",
    "2008-08",
    "2008-09",
    "2008-10",
    "2008-11",
    "2008-12",
    "2009-01",
    "2009-02",
    "2009-03",
    "2009-04",
    "2009-05",
    "2009-06",
    "2009-07",
    "2009-08",
    "2009-09",
    "2009-10",
    "2009-11",
    "2009-12",
    "2010-01",
    "2010-02",
    "2010-03",
    "2010-04",
    "2010-05",
    "2010-06",
    "2010-07",
    "2010-08",
    "2010-09",
    "2010-10",
    "2010-11",
    "2010-12",
    "2011-01",
    "2011-02",
    "2011-03",
    "2011-04",
    "2011-05",
    "2011-06",
    "2011-07",
    "2011-08",
    "2011-09",
    "2011-10",
    "2011-11",
    "2011-12",
    "2012-01",
    "2012-02",
    "2012-03",
    "2012-04",
    "2012-05",
    "2012-06",
    "2012-07",
    "2012-08",
    "2012-09",
    "2012-10",
    "2012-11",
    "2012-12",
    "2013-01",
    "2013-02",
    "2013-03",
    "2013-04",
    "2013-05",
    "2013-06",
    "2013-07",
    "2013-08",
    "2013-09",
    "2013-10",
    "2013-11",
    "2013-12",
    "2014-01",
    "2014-02",
    "2014-03",
    "2014-04",
    "2014-05",
    "2014-06",
    "2014-07",
    "2014-08",
    "2014-09",
    "2014-10",
    "2014-11",
    "2014-12",
    "2015-01",
    "2015-02",
    "2015-03",
    "2015-04",
    "2015-05",
    "2015-06",
    "2015-07",
    "2015-08",
    "2015-09",
    "2015-10",
    "2015-11",
    "2015-12",
    "2016-01",
    "2016-02",
    "2016-03",
    "2016-04",
    "2016-05",
    "2016-06",
    "2016-07",
    "2016-08",
    "2016-09",
    "2016-10",
    "2016-11",
    "2016-12",
    "2017-01",
    "2017-02",
    "2017-03",
    "2017-04",
    "2017-05",
    "2017-06",
    "2017-07",
    "2017-08",
    "2017-09",
    "2017-10",
    "2017-11",
    "2017-12",
    "2018-01",
    "2018-02",
    "2018-03",
    "2018-04",
    "2018-05",
    "2018-06",
    "2018-07",
    "2018-08",
    "2018-09",
    "2018-10",
    "2018-11",
    "2018-12",
    "2019-01",
    "2019-02",
    "2019-03",
    "2019-04",
    "2019-05",
    "2019-06",
    "2019-07",
    "2019-08",
    "2019-09",
    "2019-10",
    "2019-11",
    "2019-12",
    "2020-01",
    "2020-02",
    "2020-03",
    "2020-04",
    "2020-05",
    "2020-06",
    "2020-07",
    "2020-08",
    "2020-09",
    "2020-10",
    "2020-11",
    "2020-12",
    "2021-01",
    "2021-02",
    "2021-03",
    "2021-04",
    "2021-05",
    "2021-06",
    "2021-07",
    "2021-08",
    "2021-09",
    "2021-10",
    "2021-11",
    "2021-12",
    "2022-01",
    "2022-02",
    "2022-03",
    "2022-04",
    "2022-05",
    "2022-06",
    "2022-07",
    "2022-08",
    "2022-09",
    "2022-10",
    "2022-11",
    "2022-12",
    "2023-01",
    "2023-02",
    "2023-03",
    "2023-04",
    "2023-05",
    "2023-06",
    "2023-07",
    "2023-08",
    "2023-09",
    "2023-10",
    "2023-11",
    "2023-12",
    "2024-01",
    "2024-02",
    "2024-03",
    "2024-04",
    "2024-05",
    "2024-06",
    "2024-07",
    "2024-08",
    "2024-09",
    "2024-10",
    "2024-11",
    "2024-12",
    "2025-01",
    "2025-02",
    "2025-03",
    "2025-04",
    "2025-05",
    "2025-06",
    "2025-07",
    "2025-08",
    "2025-09",
    "2025-10",
    "2025-11",
    "2025-12",
    "2026-01",
    "2026-02",
    "2026-03",
    "2026-04",
    "2026-05",
    "2026-06",
    "2026-07"
  ],
  "holdings": {
    "2005-01": [
      "1229",
      "1314",
      "2514",
      "2612",
      "2855",
      "4532",
      "9914",
      "9945"
    ],
    "2005-02": [
      "1229",
      "2103",
      "2107",
      "2331",
      "2504",
      "2612",
      "2913",
      "4532",
      "6213",
      "9914"
    ],
    "2005-03": [
      "2107",
      "3005"
    ],
    "2005-04": [
      "1314",
      "2103",
      "2328",
      "2485"
    ],
    "2005-05": [
      "1704",
      "2103",
      "3231"
    ],
    "2005-06": [
      "1210",
      "2377",
      "3231",
      "6120"
    ],
    "2005-07": [
      "2368",
      "2534",
      "3231",
      "6188"
    ],
    "2005-09": [
      "1210",
      "1513",
      "1704",
      "2027",
      "2104",
      "2548",
      "5009",
      "6188"
    ],
    "2005-10": [
      "1210",
      "1513"
    ],
    "2005-11": [
      "1513",
      "3231"
    ],
    "2005-12": [
      "1717",
      "2103",
      "2104",
      "2301",
      "2313",
      "2355",
      "2356",
      "2450",
      "6191"
    ],
    "2006-01": [
      "1532",
      "1717",
      "2356",
      "2449"
    ],
    "2006-02": [
      "2345",
      "2356",
      "2449",
      "2489",
      "2492",
      "2542",
      "3042",
      "3231",
      "3264",
      "6191",
      "6257"
    ],
    "2006-03": [
      "1532",
      "2325",
      "2374",
      "2542",
      "2801",
      "5534"
    ],
    "2006-04": [
      "1532",
      "2103",
      "2489",
      "2542"
    ],
    "2006-05": [
      "1717",
      "1904",
      "2006",
      "2014",
      "2015",
      "2027",
      "2489",
      "6213",
      "9945"
    ],
    "2006-06": [
      "1532",
      "1605",
      "2501",
      "2520",
      "2526",
      "2612",
      "5522",
      "6213",
      "6274",
      "9945"
    ],
    "2006-07": [
      "1210",
      "2027",
      "2489",
      "9945"
    ],
    "2006-08": [
      "1504",
      "1532",
      "2014",
      "2027",
      "2504",
      "2520"
    ],
    "2006-09": [
      "1313",
      "1909",
      "2027",
      "2511",
      "2606",
      "3702"
    ],
    "2006-10": [
      "1313",
      "2027",
      "2605",
      "9914"
    ],
    "2006-11": [
      "2014",
      "2027",
      "2035",
      "2104",
      "2337",
      "2356",
      "2511",
      "5007",
      "9907",
      "9914"
    ],
    "2006-12": [
      "1409",
      "1434",
      "2515",
      "3702"
    ],
    "2007-01": [
      "1210",
      "2014",
      "2027",
      "5478"
    ],
    "2007-02": [
      "2377",
      "2520",
      "2605",
      "2845",
      "3006",
      "3231",
      "3702",
      "5478",
      "6282",
      "9933"
    ],
    "2007-03": [
      "2374",
      "2609",
      "2612"
    ],
    "2007-04": [
      "2103",
      "2374",
      "2609",
      "2612",
      "2617",
      "3006",
      "3017"
    ],
    "2007-05": [
      "1409",
      "2035",
      "2103",
      "2355",
      "2545",
      "2606",
      "3702",
      "5608",
      "6147"
    ],
    "2007-06": [
      "1210",
      "1434",
      "2027",
      "2355",
      "2489",
      "2606",
      "2905",
      "3005",
      "3702",
      "5608",
      "6147"
    ],
    "2007-07": [
      "2106",
      "2374",
      "2396",
      "2833",
      "6008",
      "6147",
      "8069",
      "8926"
    ],
    "2007-08": [
      "2103",
      "2105",
      "2106",
      "2855",
      "2885",
      "5478",
      "6005",
      "6008"
    ],
    "2007-09": [
      "1304",
      "1718",
      "2103",
      "2105",
      "2489",
      "3702",
      "5608"
    ],
    "2007-10": [
      "1216",
      "1314",
      "1710",
      "2101",
      "2355",
      "2603",
      "2903",
      "2905"
    ],
    "2007-11": [
      "1301",
      "1303",
      "1304",
      "1313",
      "1314",
      "1718",
      "2409",
      "2603",
      "2615",
      "3702",
      "5469",
      "6116"
    ],
    "2007-12": [
      "1304",
      "1802",
      "2603",
      "2823",
      "3009",
      "3702",
      "6116"
    ],
    "2008-01": [
      "2823",
      "3367"
    ],
    "2008-02": [
      "1304",
      "1440",
      "2107",
      "2108",
      "2520",
      "2834",
      "3009"
    ],
    "2008-03": [
      "2534",
      "3009"
    ],
    "2008-04": [
      "2520",
      "2854",
      "2880",
      "2891"
    ],
    "2008-05": [
      "2376",
      "2501",
      "2511",
      "2534",
      "8926",
      "9930"
    ],
    "2008-06": [
      "1104",
      "1210",
      "1227",
      "2520",
      "2834",
      "3049"
    ],
    "2008-07": [
      "2023"
    ],
    "2008-08": [
      "1210",
      "3264",
      "9939"
    ],
    "2008-09": [
      "3059",
      "9939"
    ],
    "2008-10": [
      "6282"
    ],
    "2008-11": [
      "2104",
      "2301",
      "2312",
      "3005",
      "3017",
      "8926"
    ],
    "2008-12": [
      "2377",
      "2608",
      "6282"
    ],
    "2009-01": [
      "1503",
      "1704",
      "3005"
    ],
    "2009-02": [
      "1227",
      "2515",
      "2854",
      "2905"
    ],
    "2009-03": [
      "2820",
      "6188"
    ],
    "2009-04": [
      "1310",
      "1312",
      "2548",
      "2889"
    ],
    "2009-05": [
      "1310",
      "1312",
      "1604",
      "2106",
      "2511",
      "3049",
      "3260",
      "5522"
    ],
    "2009-06": [
      "1312",
      "2027",
      "2227",
      "2499",
      "2514",
      "2542",
      "2887",
      "3702",
      "6120"
    ],
    "2009-07": [
      "1312",
      "1319",
      "1605",
      "2101",
      "2820",
      "6147",
      "6278"
    ],
    "2009-08": [
      "1451",
      "2446",
      "2855",
      "2887",
      "3005",
      "3037",
      "3702",
      "6120",
      "6147"
    ],
    "2009-09": [
      "1312",
      "1717",
      "2331",
      "2355",
      "2489",
      "3017",
      "5469",
      "6278"
    ],
    "2009-10": [
      "1312",
      "2520",
      "2542",
      "6214"
    ],
    "2009-11": [
      "1532",
      "2301",
      "2311",
      "2324",
      "2439",
      "2520",
      "3037",
      "6213"
    ],
    "2009-12": [
      "1227",
      "1736",
      "2332",
      "2401",
      "2520",
      "6214",
      "8008"
    ],
    "2010-01": [
      "1312",
      "2014",
      "2439",
      "2833",
      "3017",
      "3702"
    ],
    "2010-02": [
      "2014",
      "2107",
      "2327",
      "2344",
      "2449",
      "2492",
      "3009",
      "3010",
      "3049",
      "3264",
      "3474",
      "3481",
      "6285",
      "8131"
    ],
    "2010-03": [
      "2354",
      "2481",
      "2534",
      "3514",
      "3702",
      "6191",
      "6213"
    ],
    "2010-04": [
      "1314",
      "1532",
      "1802",
      "2103",
      "2327",
      "3264",
      "6147",
      "6191"
    ],
    "2010-05": [
      "1229",
      "1304",
      "1313",
      "1326",
      "1718",
      "2014",
      "2227",
      "2327",
      "2344",
      "2610",
      "2849",
      "3036",
      "9910"
    ],
    "2010-06": [
      "1718",
      "2327",
      "2609",
      "2615",
      "3010",
      "4128",
      "4725",
      "9907"
    ],
    "2010-07": [
      "2603",
      "2609",
      "2610",
      "2618",
      "9941"
    ],
    "2010-08": [
      "2404",
      "2603",
      "2609",
      "2610",
      "2615",
      "2618",
      "2801",
      "2809",
      "2812",
      "2845",
      "6213"
    ],
    "2010-09": [
      "1314",
      "1409",
      "2206",
      "2207",
      "2511",
      "2547",
      "2615",
      "2618",
      "2809",
      "3519",
      "5820"
    ],
    "2010-10": [
      "1229",
      "1440",
      "2227",
      "2312",
      "2345",
      "2352",
      "2481",
      "2905",
      "3010",
      "5522",
      "5534",
      "5820"
    ],
    "2010-11": [
      "1104",
      "1229",
      "1312",
      "1409",
      "1451",
      "1718",
      "1907",
      "2352",
      "2384",
      "2547",
      "2834",
      "3231",
      "5820"
    ],
    "2010-12": [
      "1229",
      "1308",
      "1312",
      "1313",
      "1314",
      "1409",
      "2392",
      "2609",
      "2618",
      "2905"
    ],
    "2011-01": [
      "1308",
      "1313",
      "1440",
      "1710",
      "1718",
      "2313",
      "2618",
      "2834",
      "2889",
      "5820",
      "6176"
    ],
    "2011-02": [
      "1308",
      "1312",
      "1314",
      "2006",
      "2107",
      "2449",
      "2548",
      "2603",
      "2801",
      "2820",
      "2834",
      "2837",
      "2838",
      "2884",
      "2885",
      "2887",
      "2889",
      "2890",
      "3519",
      "5483",
      "5820",
      "6176"
    ],
    "2011-03": [
      "1303",
      "1304",
      "1326",
      "5347"
    ],
    "2011-04": [
      "1308",
      "1504",
      "2014",
      "2106",
      "3519"
    ],
    "2011-05": [
      "1101",
      "1308",
      "2106",
      "2881",
      "3022",
      "6176"
    ],
    "2011-06": [
      "2106",
      "2823",
      "3515",
      "5009",
      "9914"
    ],
    "2011-07": [
      "2823",
      "2905"
    ],
    "2011-08": [
      "1314",
      "2206",
      "2520",
      "2905"
    ],
    "2011-09": [
      "1451",
      "2015",
      "2104",
      "2206",
      "2511"
    ],
    "2011-10": [
      "1907",
      "2377",
      "5534"
    ],
    "2011-11": [
      "4938"
    ],
    "2011-12": [
      "1907",
      "2104",
      "3703",
      "8926"
    ],
    "2012-01": [
      "1513",
      "2317",
      "2355",
      "2441",
      "9910"
    ],
    "2012-02": [
      "2317",
      "2353",
      "2355",
      "2637",
      "3231",
      "3515",
      "4532",
      "4938",
      "5871",
      "6605",
      "9933"
    ],
    "2012-03": [
      "2379",
      "2489",
      "3260",
      "8081",
      "9945"
    ],
    "2012-04": [
      "1337",
      "2355",
      "4938",
      "4960",
      "6147",
      "9945"
    ],
    "2012-05": [
      "2345",
      "2439",
      "2489",
      "4960",
      "5009",
      "5347",
      "8926",
      "9945"
    ],
    "2012-06": [
      "2383",
      "2890",
      "3005",
      "5347"
    ],
    "2012-07": [
      "9945"
    ],
    "2012-08": [
      "2355",
      "2377",
      "2449",
      "5534",
      "9904"
    ],
    "2012-09": [
      "2449",
      "2545",
      "2838",
      "2915",
      "3376",
      "5871",
      "6282"
    ],
    "2012-10": [
      "1104",
      "1312",
      "2106",
      "2545",
      "2890",
      "9910"
    ],
    "2012-11": [
      "1312",
      "2357",
      "3533",
      "5347",
      "5534",
      "6271",
      "6282",
      "9910"
    ],
    "2012-12": [
      "1104",
      "1904",
      "2317",
      "2392",
      "2545",
      "2890",
      "2905",
      "5871"
    ],
    "2013-01": [
      "1104",
      "1440",
      "1532",
      "2547",
      "2849",
      "6147"
    ],
    "2013-02": [
      "1532",
      "1907",
      "2014",
      "2344",
      "2534",
      "2547",
      "2548",
      "2609",
      "2812",
      "2883",
      "2885",
      "3481",
      "5347",
      "5820"
    ],
    "2013-03": [
      "2014",
      "2534",
      "2882",
      "3481",
      "6271"
    ],
    "2013-04": [
      "2451",
      "2501",
      "2882",
      "2888",
      "3698",
      "5534"
    ],
    "2013-05": [
      "2301",
      "2379",
      "2534",
      "2548",
      "5483",
      "9907"
    ],
    "2013-06": [
      "1532",
      "2303",
      "2356",
      "2888",
      "3006",
      "3260",
      "3481",
      "4938",
      "5347",
      "6116"
    ],
    "2013-07": [
      "2356",
      "2439",
      "3006",
      "3049",
      "6116"
    ],
    "2013-08": [
      "1312",
      "1319",
      "2107",
      "2303",
      "2377",
      "9938"
    ],
    "2013-09": [
      "1310",
      "1312",
      "2356",
      "2485",
      "2887",
      "2891",
      "3260",
      "9938"
    ],
    "2013-10": [
      "1310",
      "2312",
      "2331",
      "2377",
      "2887",
      "3260",
      "6214",
      "9904"
    ],
    "2013-11": [
      "1312",
      "2312",
      "6202"
    ],
    "2013-12": [
      "1101",
      "1310",
      "1513",
      "2313",
      "2324",
      "3576",
      "3706",
      "5483",
      "6285",
      "9907"
    ],
    "2014-01": [
      "1717",
      "2107",
      "2331",
      "2809"
    ],
    "2014-02": [
      "1717",
      "1909",
      "2352",
      "2371",
      "2377",
      "5531",
      "6188"
    ],
    "2014-03": [
      "2357",
      "2474",
      "5478"
    ],
    "2014-04": [
      "1589",
      "2107",
      "2371",
      "2377",
      "3059",
      "5371",
      "6282",
      "9925"
    ],
    "2014-05": [
      "2327",
      "2344",
      "2499",
      "4915",
      "8069"
    ],
    "2014-06": [
      "1736",
      "2027",
      "2303",
      "2377",
      "2409",
      "2441",
      "4915",
      "4938"
    ],
    "2014-07": [
      "1210",
      "2035",
      "2312",
      "2327",
      "2352",
      "2377",
      "2489",
      "4915",
      "6257",
      "8926"
    ],
    "2014-08": [
      "2027",
      "2327",
      "2353",
      "2377",
      "2409",
      "3481"
    ],
    "2014-09": [
      "2027",
      "2104",
      "2353",
      "2441",
      "2615",
      "2849",
      "2881",
      "2891",
      "3036",
      "5371"
    ],
    "2014-10": [
      "2027",
      "2035",
      "2312",
      "2331",
      "2352",
      "2542",
      "2615",
      "2882",
      "8926"
    ],
    "2014-11": [
      "2104",
      "2327",
      "2331",
      "2383",
      "2409",
      "2615",
      "3481",
      "3533"
    ],
    "2014-12": [
      "2317",
      "2354",
      "2881",
      "2891",
      "3481",
      "4938",
      "9904"
    ],
    "2015-01": [
      "1234",
      "2027",
      "2107",
      "2327",
      "2352",
      "2603",
      "2615",
      "2905",
      "8926"
    ],
    "2015-02": [
      "2303",
      "2368",
      "2409",
      "2542",
      "2603",
      "2609",
      "2610",
      "2618",
      "2833",
      "3673",
      "3698",
      "4938",
      "6269"
    ],
    "2015-03": [
      "1532",
      "1718",
      "2344",
      "2542",
      "2610",
      "2618",
      "2905",
      "6120"
    ],
    "2015-04": [
      "1312",
      "2324",
      "2383",
      "2451",
      "2474",
      "2501",
      "2609",
      "2610",
      "2615",
      "2618",
      "4938"
    ],
    "2015-05": [
      "1905",
      "2383",
      "2615",
      "2833",
      "2881",
      "2885",
      "2915",
      "6269",
      "8046",
      "9945"
    ],
    "2015-06": [
      "1312",
      "2354",
      "2534",
      "2823",
      "2881",
      "2882",
      "3005",
      "3376",
      "3481",
      "3706"
    ],
    "2015-07": [
      "1704",
      "2108",
      "2383",
      "2515",
      "2833",
      "2867",
      "3706"
    ],
    "2015-08": [
      "1326",
      "2313",
      "2637",
      "6269"
    ],
    "2015-09": [
      "2867",
      "2881",
      "2882",
      "5522"
    ],
    "2015-10": [
      "1229",
      "2108",
      "2608",
      "2867",
      "2905"
    ],
    "2015-11": [
      "1704",
      "2345",
      "2377",
      "3105"
    ],
    "2015-12": [
      "1704",
      "2377",
      "2867",
      "3044",
      "5483",
      "8069"
    ],
    "2016-01": [
      "1409",
      "1704",
      "2345",
      "2377",
      "2485",
      "2492",
      "6605",
      "9945"
    ],
    "2016-02": [
      "2345",
      "2408",
      "3514",
      "5264",
      "5483"
    ],
    "2016-03": [
      "1319",
      "2355",
      "2485",
      "3514",
      "3576",
      "5371"
    ],
    "2016-04": [
      "1234",
      "1605",
      "1909",
      "2377",
      "2492",
      "3042"
    ],
    "2016-05": [
      "1532",
      "1704",
      "2023",
      "2404",
      "2489",
      "2492",
      "3042",
      "5534",
      "8131"
    ],
    "2016-06": [
      "1210",
      "1605",
      "1909",
      "2312",
      "2345",
      "2511",
      "3474",
      "3596",
      "5434"
    ],
    "2016-07": [
      "2439",
      "5534"
    ],
    "2016-08": [
      "1909",
      "2377",
      "2379",
      "2439",
      "2449",
      "2542",
      "3260",
      "6213"
    ],
    "2016-09": [
      "1215",
      "1605",
      "1704",
      "2023",
      "2328",
      "2352",
      "2545",
      "3005",
      "4532"
    ],
    "2016-10": [
      "2023",
      "2489",
      "2492",
      "2823",
      "2881",
      "3231",
      "3706",
      "4532"
    ],
    "2016-11": [
      "1305",
      "1313",
      "1326",
      "2023",
      "2408",
      "3260",
      "6116",
      "6176"
    ],
    "2016-12": [
      "1215",
      "1304",
      "1310",
      "1312",
      "1605",
      "2006",
      "2014",
      "2301",
      "2352",
      "2823",
      "2867",
      "2905",
      "3036",
      "5534",
      "6005",
      "6116"
    ],
    "2017-01": [
      "1303",
      "1312",
      "1313",
      "2023",
      "2376",
      "3260",
      "5534",
      "6116",
      "6456"
    ],
    "2017-02": [
      "1229",
      "1314",
      "1710",
      "1718",
      "1907",
      "1909",
      "2337",
      "2344",
      "2352",
      "2548",
      "3019",
      "3231",
      "3260",
      "3406",
      "3481",
      "3706",
      "5534",
      "6116",
      "6214",
      "6456"
    ],
    "2017-03": [
      "1314",
      "1909",
      "2023",
      "2337",
      "3673",
      "5371"
    ],
    "2017-04": [
      "1215",
      "1904",
      "2352",
      "2913",
      "3260",
      "6274"
    ],
    "2017-05": [
      "1229",
      "2327",
      "2392",
      "2606",
      "3260",
      "3481",
      "6005"
    ],
    "2017-06": [
      "1215",
      "2327",
      "2504",
      "2603",
      "2633",
      "3260",
      "3481",
      "3706",
      "8150"
    ],
    "2017-07": [
      "2313",
      "2408",
      "2504",
      "2603",
      "3481",
      "8299"
    ],
    "2017-08": [
      "2352",
      "2408",
      "2603",
      "5483",
      "6269"
    ],
    "2017-09": [
      "2104",
      "2327",
      "2534",
      "2603",
      "2610"
    ],
    "2017-10": [
      "1229",
      "1909",
      "2104",
      "2327",
      "2373",
      "2408",
      "6116"
    ],
    "2017-11": [
      "1313",
      "2303",
      "2327",
      "2373",
      "2376",
      "2408"
    ],
    "2017-12": [
      "1313",
      "1605",
      "1718",
      "1907",
      "2353",
      "2905",
      "3026",
      "6005",
      "8131",
      "8415",
      "9940"
    ],
    "2018-01": [
      "1326",
      "1710",
      "2376",
      "2534",
      "2915",
      "3026",
      "9945"
    ],
    "2018-02": [
      "1229",
      "1802",
      "2014",
      "2027",
      "3026",
      "5483",
      "5534",
      "6120",
      "6147",
      "6274"
    ],
    "2018-03": [
      "1301",
      "1326",
      "2888",
      "3037",
      "5371",
      "5483",
      "6257"
    ],
    "2018-04": [
      "2027",
      "2377",
      "2888",
      "3026",
      "4123",
      "5534",
      "6147"
    ],
    "2018-05": [
      "1102",
      "1605",
      "1808",
      "2027",
      "2408",
      "2888",
      "2903",
      "4123"
    ],
    "2018-06": [
      "1101",
      "1210",
      "1313",
      "1808",
      "1904",
      "2347",
      "2362",
      "2376",
      "2534",
      "4123",
      "8163"
    ],
    "2018-07": [
      "1409",
      "2303",
      "2456",
      "3596",
      "8163",
      "8415"
    ],
    "2018-08": [
      "1102",
      "1808",
      "2303",
      "2915"
    ],
    "2018-09": [
      "1402",
      "1409",
      "1718",
      "1904",
      "2108",
      "2542",
      "2547",
      "2915"
    ],
    "2018-10": [
      "1904",
      "2547",
      "2633",
      "6176"
    ],
    "2018-11": [
      "2027",
      "2501",
      "2834",
      "2915",
      "6176"
    ],
    "2018-12": [
      "2404",
      "2501",
      "2547",
      "2618",
      "2834",
      "2915",
      "3037",
      "4958",
      "5522",
      "8150",
      "9945"
    ],
    "2019-01": [
      "2610",
      "2885",
      "3037",
      "6176"
    ],
    "2019-02": [
      "1795",
      "2548",
      "2610",
      "3533",
      "6278",
      "8046",
      "8150"
    ],
    "2019-03": [
      "5534",
      "6188",
      "6412"
    ],
    "2019-04": [
      "2392",
      "2439",
      "3231",
      "3596",
      "6147",
      "6176"
    ],
    "2019-05": [
      "1201",
      "2392",
      "2501",
      "5876",
      "6176",
      "9938"
    ],
    "2019-06": [
      "1736",
      "2201",
      "2520",
      "2615",
      "2845",
      "2923",
      "3703",
      "5469"
    ],
    "2019-07": [
      "1201",
      "1229",
      "2385",
      "3653",
      "6278"
    ],
    "2019-08": [
      "1215",
      "2303",
      "2313",
      "2337",
      "2449",
      "2548",
      "6176",
      "6278"
    ],
    "2019-09": [
      "1215",
      "2101",
      "2385",
      "2539",
      "6257",
      "8150"
    ],
    "2019-10": [
      "1304",
      "2313",
      "6176"
    ],
    "2019-11": [
      "2337",
      "2905",
      "9802"
    ],
    "2019-12": [
      "2313",
      "2392",
      "2905",
      "3413",
      "4938",
      "5469"
    ],
    "2020-01": [
      "1210",
      "2504",
      "3413",
      "6452"
    ],
    "2020-02": [
      "1210",
      "2337",
      "2504",
      "2809",
      "5483",
      "6239",
      "6278",
      "9939"
    ],
    "2020-03": [
      "1773",
      "2303",
      "3532",
      "3706"
    ],
    "2020-04": [
      "1904",
      "2356",
      "2368",
      "5534"
    ],
    "2020-05": [
      "2303",
      "2327",
      "2368",
      "2371",
      "3042",
      "3515",
      "8046"
    ],
    "2020-06": [
      "1773",
      "2368",
      "3026",
      "6257"
    ],
    "2020-07": [
      "2376",
      "2809",
      "3189",
      "3413",
      "6196",
      "8046"
    ],
    "2020-08": [
      "2303",
      "2308",
      "2313",
      "2368",
      "4123",
      "8046"
    ],
    "2020-09": [
      "1312",
      "2108",
      "2353",
      "2377",
      "2520",
      "2603",
      "2609",
      "2615",
      "3017",
      "3703"
    ],
    "2020-10": [
      "1304",
      "1312",
      "1513",
      "1605",
      "2006",
      "2368",
      "2504",
      "2603",
      "2609",
      "2615",
      "3264",
      "3703",
      "4128",
      "6116"
    ],
    "2020-11": [
      "1312",
      "1904",
      "2204",
      "2303",
      "2353",
      "2357",
      "2504",
      "2603",
      "2609"
    ],
    "2020-12": [
      "1304",
      "1312",
      "1313",
      "2105",
      "2108",
      "2204",
      "2352",
      "2603",
      "2609",
      "2615",
      "2723",
      "6257"
    ],
    "2021-01": [
      "1313",
      "1802",
      "2428",
      "2492",
      "2603",
      "2609",
      "3545",
      "6116"
    ],
    "2021-02": [
      "1313",
      "1802",
      "2014",
      "2317",
      "2352",
      "2409",
      "2603",
      "2609",
      "2610",
      "2615",
      "3481",
      "5483"
    ],
    "2021-03": [
      "2014",
      "2027",
      "2344",
      "2409",
      "2603",
      "2609",
      "2615",
      "3481",
      "3545",
      "3711",
      "5371"
    ],
    "2021-04": [
      "1305",
      "1312",
      "1409",
      "1440",
      "2014",
      "2103",
      "2204",
      "2352",
      "2357",
      "2377",
      "2409",
      "2603",
      "2609",
      "2637",
      "3481",
      "6116",
      "8150"
    ],
    "2021-05": [
      "1303",
      "1440",
      "1605",
      "1905",
      "2002",
      "2014",
      "2023",
      "2103",
      "2409",
      "2603",
      "2610",
      "2615",
      "2637",
      "2881",
      "3036",
      "3042",
      "3481",
      "6005",
      "6116"
    ],
    "2021-06": [
      "1304",
      "1907",
      "2027",
      "2103",
      "2204",
      "2357",
      "2376",
      "2409",
      "2603",
      "2881",
      "2882",
      "2883",
      "2889",
      "3481",
      "4919",
      "8415"
    ],
    "2021-07": [
      "1313",
      "1409",
      "2002",
      "2014",
      "2023",
      "2027",
      "2481",
      "2605",
      "2618",
      "3515",
      "6116"
    ],
    "2021-08": [
      "2609",
      "2883"
    ],
    "2021-09": [
      "1312",
      "2511",
      "2603",
      "2609",
      "2637",
      "2881",
      "2882",
      "2887",
      "2915",
      "3036",
      "8150",
      "8415",
      "9907",
      "9941",
      "9945"
    ],
    "2021-10": [
      "1303",
      "1304",
      "2838",
      "2915"
    ],
    "2021-11": [
      "1301",
      "1722",
      "2883",
      "3036",
      "4123"
    ],
    "2021-12": [
      "2610",
      "2618",
      "2823",
      "2915",
      "3010",
      "3706"
    ],
    "2022-01": [
      "2103",
      "2888"
    ],
    "2022-02": [
      "2610",
      "2618",
      "3036",
      "3596",
      "3665",
      "3714",
      "4927",
      "6182",
      "6278"
    ],
    "2022-03": [
      "2603",
      "2880",
      "3010",
      "3592"
    ],
    "2022-04": [
      "2385",
      "2504",
      "2915",
      "3017",
      "8112",
      "9933",
      "9945"
    ],
    "2022-05": [
      "1605",
      "2504",
      "2603",
      "2609",
      "9802"
    ],
    "2022-06": [
      "1319",
      "2206",
      "2313",
      "2449",
      "2607",
      "2609",
      "2637",
      "2897"
    ],
    "2022-07": [
      "1301",
      "2106",
      "2206",
      "5534"
    ],
    "2022-08": [
      "2301",
      "9802"
    ],
    "2022-09": [
      "1513",
      "2059",
      "2211",
      "3231",
      "3703",
      "4958",
      "5371",
      "5388",
      "9907"
    ],
    "2022-10": [
      "2474",
      "2834",
      "3231",
      "3376",
      "3703",
      "5434",
      "6176",
      "6285"
    ],
    "2022-11": [
      "2474",
      "2834",
      "6176",
      "6285"
    ],
    "2022-12": [
      "1907",
      "2206",
      "2392",
      "2474",
      "2834",
      "3706",
      "6269",
      "6285",
      "8415",
      "9904"
    ],
    "2023-01": [
      "6147",
      "6670"
    ],
    "2023-02": [
      "1909",
      "2014",
      "2201",
      "2204",
      "2887",
      "5483",
      "8436",
      "9945"
    ],
    "2023-03": [
      "1605",
      "2006",
      "5009",
      "6282"
    ],
    "2023-04": [
      "1304",
      "1504",
      "3005",
      "3592",
      "8926"
    ],
    "2023-05": [
      "1210",
      "2204",
      "6005"
    ],
    "2023-06": [
      "2393",
      "2610",
      "2618",
      "6214",
      "8926"
    ],
    "2023-07": [
      "2211",
      "2393",
      "2610",
      "2618",
      "6191",
      "8112"
    ],
    "2023-08": [
      "1319",
      "2603",
      "8112"
    ],
    "2023-09": [
      "2704",
      "2855",
      "6005",
      "6257",
      "6605"
    ],
    "2023-10": [
      "1319",
      "2885"
    ],
    "2023-11": [
      "1319",
      "2363",
      "2603",
      "3260",
      "6176",
      "6239"
    ],
    "2023-12": [
      "2492",
      "3227",
      "3702",
      "6191",
      "6257",
      "6605"
    ],
    "2024-01": [
      "2211",
      "2520",
      "2603",
      "6257",
      "8112"
    ],
    "2024-02": [
      "2313",
      "2520",
      "2637",
      "3036",
      "3711",
      "6274",
      "8112",
      "8299"
    ],
    "2024-03": [
      "2439",
      "2504",
      "2637",
      "2809",
      "2891",
      "3036",
      "6257",
      "8070",
      "8926"
    ],
    "2024-04": [
      "2501",
      "2504",
      "2603",
      "2809",
      "3592"
    ],
    "2024-05": [
      "2363",
      "2371",
      "2501",
      "2515",
      "2520",
      "2603",
      "2637",
      "2855",
      "5522",
      "6005",
      "6670"
    ],
    "2024-06": [
      "2362",
      "2451",
      "2603",
      "2609",
      "2615",
      "2704",
      "2867",
      "2882",
      "9904",
      "9945"
    ],
    "2024-07": [
      "2449",
      "2542",
      "2609",
      "2637",
      "2855",
      "6605",
      "8255"
    ],
    "2024-08": [
      "2327",
      "2393",
      "2609",
      "2610",
      "2615",
      "2637",
      "6670",
      "9945"
    ],
    "2024-09": [
      "2312",
      "2357",
      "2474",
      "2504",
      "2520",
      "2545",
      "2615",
      "2881",
      "2882",
      "2905",
      "2915",
      "3019",
      "3227"
    ],
    "2024-10": [
      "2603",
      "2615",
      "2812",
      "2881",
      "2882",
      "2883",
      "2888",
      "3413"
    ],
    "2024-11": [
      "2603",
      "2618",
      "2637",
      "6176",
      "9938"
    ],
    "2024-12": [
      "2312",
      "2357",
      "2520",
      "2545",
      "2603",
      "2618",
      "2881",
      "3211",
      "3706"
    ],
    "2025-01": [
      "2393",
      "2609",
      "2883",
      "3515"
    ],
    "2025-02": [
      "2328",
      "2377",
      "2723",
      "3036",
      "3231",
      "3711",
      "9802"
    ],
    "2025-03": [
      "5371",
      "6214"
    ],
    "2025-04": [
      "1102",
      "1210",
      "2002",
      "2603",
      "2883",
      "3260",
      "5388",
      "5530"
    ],
    "2025-05": [
      "2027",
      "2474",
      "9907"
    ],
    "2025-06": [
      "2603",
      "5469",
      "9907"
    ],
    "2025-07": [
      "6191",
      "6257"
    ],
    "2025-08": [
      "3260",
      "3706",
      "9907"
    ],
    "2025-09": [
      "2374",
      "3260",
      "8926"
    ],
    "2025-10": [
      "3260",
      "6456"
    ],
    "2025-11": [
      "2408",
      "2492",
      "3105"
    ],
    "2025-12": [
      "1409",
      "2211",
      "2344",
      "2881",
      "2885",
      "3260",
      "5469",
      "6505",
      "8131"
    ],
    "2026-01": [
      "2548",
      "2882",
      "2883",
      "2887",
      "5522"
    ],
    "2026-02": [
      "1303",
      "1326",
      "1802",
      "2014",
      "2312",
      "2867",
      "4958",
      "6239",
      "6505",
      "6770",
      "8112",
      "8131",
      "8150"
    ],
    "2026-03": [
      "1303",
      "2605",
      "2855",
      "3576",
      "6282",
      "8150"
    ],
    "2026-04": [
      "1723",
      "2355",
      "2489",
      "2605",
      "3006",
      "3026",
      "3702",
      "6147",
      "9933"
    ],
    "2026-05": [
      "1326",
      "2303",
      "2485",
      "2605",
      "2883",
      "2885",
      "3481",
      "6147"
    ],
    "2026-06": [
      "2312",
      "2376",
      "2855",
      "3036",
      "3702",
      "8926"
    ],
    "2026-07": [
      "1303",
      "1718",
      "2855",
      "8016",
      "8926"
    ]
  }
}